mergelib/__init__.py
mergelib/coefficients.py
mergelib/merge.py
mergelib/utils.py
mergelib/engine/__init__.py
mergelib/engine/fisher.py
mergelib-0.0.1a0.dist-info/METADATA
mergelib-0.0.1a0.dist-info/WHEEL
mergelib-0.0.1a0.dist-info/top_level.txt
mergelib-0.0.1a0.dist-info/RECORD
